hypothesis_testing_tool/__init__.py
hypothesis_testing_tool/compute_stats/__init__.py
hypothesis_testing_tool/compute_stats/one_sample_statistics.py
hypothesis_testing_tool/compute_stats/two_sample_statistics.py
hypothesis_testing_tool/presentation/__init__.py
hypothesis_testing_tool/presentation/create_plots.py
hypothesis_testing_tool-0.1.2.dist-info/METADATA
hypothesis_testing_tool-0.1.2.dist-info/WHEEL
hypothesis_testing_tool-0.1.2.dist-info/RECORD
