Metadata-Version: 2.1
Name: hypothesis-testing-tool
Version: 0.1.2
Summary: A tool for doing hypothesis testing
Author: Alexandros Vamvakaris-Skrivanos
Author-email: vamvas@outlook.com.gr
Requires-Python: >=3.11,<4.0
Classifier: Programming Language :: Python :: 3
Classifier: Programming Language :: Python :: 3.11
Classifier: Programming Language :: Python :: 3.12
Requires-Dist: matplotlib (>=3.9.1,<4.0.0)
Requires-Dist: scipy (>=1.14.0,<2.0.0)
